amphi/__init__.py
amphi/amphi.py
amphi/version.py
amphi-1.0.15.dist-info/LICENSE
amphi-1.0.15.dist-info/METADATA
amphi-1.0.15.dist-info/WHEEL
amphi-1.0.15.dist-info/top_level.txt
amphi-1.0.15.dist-info/RECORD
