Metadata-Version: 2.1
Name: amphi
Version: 1.0.15
Summary: MoviePy OOP wrapper
Home-page: https://github.com/rmaniego/amphi
Author: Rodney Maniego Jr.
Author-email: rod.maniego23@gmail.com
License: MIT
Download-URL: https://github.com/rmaniego/amphi/archive/v1.0.tar.gz
Keywords: MoviePy,Video,Editor
Platform: UNKNOWN
Classifier: Development Status :: 5 - Production/Stable
Classifier: Intended Audience :: Developers
Classifier: Topic :: Software Development :: Build Tools
Classifier: License :: OSI Approved :: MIT License
Classifier: Programming Language :: Python :: 3
Requires-Python: >=3.6
License-File: LICENSE
Requires-Dist: moviepy
Requires-Dist: vidstab
Requires-Dist: sometime
